snowflake_snowpark_python-1.25.0-py3.11-nspkg.pth
snowflake/snowpark/__init__.py
snowflake/snowpark/async_job.py
snowflake/snowpark/column.py
snowflake/snowpark/context.py
snowflake/snowpark/dataframe.py
snowflake/snowpark/dataframe_analytics_functions.py
snowflake/snowpark/dataframe_na_functions.py
snowflake/snowpark/dataframe_reader.py
snowflake/snowpark/dataframe_stat_functions.py
snowflake/snowpark/dataframe_writer.py
snowflake/snowpark/exceptions.py
snowflake/snowpark/file_operation.py
snowflake/snowpark/files.py
snowflake/snowpark/functions.py
snowflake/snowpark/lineage.py
snowflake/snowpark/py.typed
snowflake/snowpark/query_history.py
snowflake/snowpark/relational_grouped_dataframe.py
snowflake/snowpark/row.py
snowflake/snowpark/session.py
snowflake/snowpark/stored_procedure.py
snowflake/snowpark/stored_procedure_profiler.py
snowflake/snowpark/table.py
snowflake/snowpark/table_function.py
snowflake/snowpark/testing.py
snowflake/snowpark/types.py
snowflake/snowpark/udaf.py
snowflake/snowpark/udf.py
snowflake/snowpark/udtf.py
snowflake/snowpark/version.py
snowflake/snowpark/window.py
snowflake/snowpark/_internal/__init__.py
snowflake/snowpark/_internal/code_generation.py
snowflake/snowpark/_internal/error_message.py
snowflake/snowpark/_internal/open_telemetry.py
snowflake/snowpark/_internal/packaging_utils.py
snowflake/snowpark/_internal/select_projection_complexity_utils.py
snowflake/snowpark/_internal/server_connection.py
snowflake/snowpark/_internal/telemetry.py
snowflake/snowpark/_internal/temp_table_auto_cleaner.py
snowflake/snowpark/_internal/type_utils.py
snowflake/snowpark/_internal/udf_utils.py
snowflake/snowpark/_internal/utils.py
snowflake/snowpark/_internal/analyzer/__init__.py
snowflake/snowpark/_internal/analyzer/analyzer.py
snowflake/snowpark/_internal/analyzer/analyzer_utils.py
snowflake/snowpark/_internal/analyzer/binary_expression.py
snowflake/snowpark/_internal/analyzer/binary_plan_node.py
snowflake_snowpark_python-1.25.0.dist-info/LICENSE.txt
snowflake_snowpark_python-1.25.0.dist-info/METADATA
snowflake_snowpark_python-1.25.0.dist-info/WHEEL
snowflake_snowpark_python-1.25.0.dist-info/namespace_packages.txt
snowflake_snowpark_python-1.25.0.dist-info/top_level.txt
snowflake_snowpark_python-1.25.0.dist-info/RECORD
