Metadata-Version: 2.1
Name: snowflake-snowpark-python
Version: 1.25.0
Summary: Snowflake Snowpark for Python
Home-page: https://www.snowflake.com/
Author: Snowflake, Inc
Author-email: snowflake-python-libraries-dl@snowflake.com
License: Apache License, Version 2.0
Project-URL: Documentation, https://docs.snowflake.com/en/developer-guide/snowpark/python/index.html
Project-URL: Source, https://github.com/snowflakedb/snowpark-python
Project-URL: Issues, https://github.com/snowflakedb/snowpark-python/issues
Project-URL: Changelog, https://github.com/snowflakedb/snowpark-python/blob/main/CHANGELOG.md
Keywords: Snowflake db database cloud analytics warehouse
Classifier: Development Status :: 5 - Production/Stable
Classifier: Environment :: Console
Classifier: Environment :: Other Environment
Classifier: Intended Audience :: Developers
Classifier: Intended Audience :: Education
Classifier: Intended Audience :: Information Technology
Classifier: Intended Audience :: System Administrators
Classifier: License :: OSI Approved :: Apache Software License
Classifier: Operating System :: OS Independent
Classifier: Programming Language :: SQL
Classifier: Programming Language :: Python :: 3 :: Only
Classifier: Programming Language :: Python :: 3.8
Classifier: Programming Language :: Python :: 3.9
Classifier: Programming Language :: Python :: 3.10
Classifier: Programming Language :: Python :: 3.11
Classifier: Topic :: Database
Classifier: Topic :: Software Development
Classifier: Topic :: Software Development :: Libraries
Classifier: Topic :: Software Development :: Libraries :: Application Frameworks
Classifier: Topic :: Software Development :: Libraries :: Python Modules
Classifier: Topic :: Scientific/Engineering :: Information Analysis
Requires-Python: >=3.8, <3.12
License-File: LICENSE.txt
Requires-Dist: setuptools>=40.6.0
Requires-Dist: wheel
Requires-Dist: snowflake-connector-python<4.0.0,>=3.12.0
Requires-Dist: typing-extensions<5.0.0,>=4.1.0
Requires-Dist: pyyaml
Requires-Dist: cloudpickle!=2.1.0,!=2.2.0,<=2.2.1,>=1.6.0; python_version < "3.11"
Requires-Dist: cloudpickle==2.2.1; python_version ~= "3.11"
Requires-Dist: protobuf<6,>=3.20
Requires-Dist: tzlocal
Provides-Extra: pandas
Requires-Dist: snowflake-connector-python[pandas]<4.0.0,>=3.12.0; extra == "pandas"
Provides-Extra: modin
Requires-Dist: snowflake-connector-python[pandas]<4.0.0,>=3.12.0; extra == "modin"
Requires-Dist: modin==0.30.1; extra == "modin"
Provides-Extra: secure-local-storage
Requires-Dist: snowflake-connector-python[secure-local-storage]<4.0.0,>=3.12.0; extra == "secure-local-storage"
Provides-Extra: development
Requires-Dist: pytest<8.0.0; extra == "development"
Requires-Dist: pytest-cov; extra == "development"
Requires-Dist: coverage; extra == "development"
Requires-Dist: sphinx==5.0.2; extra == "development"
Requires-Dist: cachetools; extra == "development"
Requires-Dist: pytest-timeout; extra == "development"
Requires-Dist: pytest-xdist; extra == "development"
Requires-Dist: openpyxl; extra == "development"
Requires-Dist: matplotlib; extra == "development"
Requires-Dist: pre-commit; extra == "development"
Requires-Dist: graphviz; extra == "development"
Requires-Dist: pytest-assume; extra == "development"
Requires-Dist: decorator; extra == "development"
Requires-Dist: protoc-wheel-0==21.1; extra == "development"
Requires-Dist: mypy-protobuf; extra == "development"
Requires-Dist: lxml; extra == "development"
Provides-Extra: modin-development
Requires-Dist: snowflake-connector-python[pandas]<4.0.0,>=3.12.0; extra == "modin-development"
Requires-Dist: modin==0.30.1; extra == "modin-development"
Requires-Dist: pytest<8.0.0; extra == "modin-development"
Requires-Dist: pytest-cov; extra == "modin-development"
Requires-Dist: coverage; extra == "modin-development"
Requires-Dist: sphinx==5.0.2; extra == "modin-development"
Requires-Dist: cachetools; extra == "modin-development"
Requires-Dist: pytest-timeout; extra == "modin-development"
Requires-Dist: pytest-xdist; extra == "modin-development"
Requires-Dist: openpyxl; extra == "modin-development"
Requires-Dist: matplotlib; extra == "modin-development"
Requires-Dist: pre-commit; extra == "modin-development"
Requires-Dist: graphviz; extra == "modin-development"
Requires-Dist: pytest-assume; extra == "modin-development"
Requires-Dist: decorator; extra == "modin-development"
Requires-Dist: protoc-wheel-0==21.1; extra == "modin-development"
Requires-Dist: mypy-protobuf; extra == "modin-development"
Requires-Dist: lxml; extra == "modin-development"
Requires-Dist: scipy; extra == "modin-development"
Requires-Dist: statsmodels; extra == "modin-development"
Requires-Dist: scikit-learn==1.5.2; extra == "modin-development"
Provides-Extra: localtest
Requires-Dist: pandas; extra == "localtest"
Requires-Dist: requests; extra == "localtest"
Provides-Extra: opentelemetry
Requires-Dist: opentelemetry-api<2.0.0,>=1.0.0; extra == "opentelemetry"
Requires-Dist: opentelemetry-sdk<2.0.0,>=1.0.0; extra == "opentelemetry"
